enhanced_dir.py
enhanced_dir-0.0.9.dist-info/METADATA
enhanced_dir-0.0.9.dist-info/WHEEL
enhanced_dir-0.0.9.dist-info/top_level.txt
enhanced_dir-0.0.9.dist-info/RECORD
