Metadata-Version: 2.1
Name: enhanced_dir
Version: 0.0.9
Summary: A enhanced version of dir, which gives more details
Home-page: UNKNOWN
License: UNKNOWN
Platform: UNKNOWN
